chameleon_engine/__init__.py
chameleon_engine/cli.py
chameleon_engine/orchestrator.py
chameleon_engine/orchestrator_examples.py
chameleon_engine/proxy_launcher.py
chameleon_engine/proxy_loader.py
chameleon_engine/behavior/__init__.py
chameleon_engine/behavior/keyboard.py
chameleon_engine/behavior/keyboard_examples.py
chameleon_engine/behavior/mouse.py
chameleon_engine/behavior/mouse_examples.py
chameleon_engine/binaries/__init__.py
chameleon_engine/binary/__init__.py
chameleon_engine/core/__init__.py
chameleon_engine/core/browser_manager.py
chameleon_engine/core/browser_manager_examples.py
chameleon_engine/core/profiles.py
chameleon_engine/fingerprinting/__init__.py
chameleon_engine/fingerprinting/generator.py
chameleon_engine/fingerprinting/generator_examples.py
chameleon_engine/fingerprinting/data/__init__.py
chameleon_engine/network/__init__.py
chameleon_engine/network/http2_rewriter.py
chameleon_engine/network/obfuscator.py
chameleon_engine/network/obfuscator_examples.py
chameleon_engine/network/proxy_integration.py
chameleon_engine/network/tls_fingerprint.py
chameleon_engine/services/__init__.py
chameleon_engine/services/binary/__init__.py
chameleon_engine/services/binary/config.py
chameleon_engine/services/binary/downloader.py
chameleon_engine/services/binary/manager.py
chameleon_engine/services/binary/manager_examples.py
chameleon_engine/services/binary/validator.py
chameleon_engine/services/database/__init__.py
chameleon_engine/services/database/models.py
chameleon_engine/services/database/utils.py
chameleon_engine/services/fingerprint/__init__.py
chameleon_engine/services/fingerprint/client.py
chameleon_engine/services/fingerprint/client_examples.py
chameleon_engine/services/fingerprint/models.py
chameleon_engine/services/fingerprint/collectors/__init__.py
chameleon_engine/services/fingerprint/collectors/network.py
chameleon_engine/services/fingerprint/collectors/real_world.py
chameleon_engine/services/fingerprint/collectors/service.py
chameleon_engine-1.0.0.dist-info/licenses/LICENSE
chameleon_engine-1.0.0.dist-info/METADATA
chameleon_engine-1.0.0.dist-info/WHEEL
chameleon_engine-1.0.0.dist-info/entry_points.txt
chameleon_engine-1.0.0.dist-info/top_level.txt
chameleon_engine-1.0.0.dist-info/RECORD
