Metadata-Version: 2.4
Name: chameleon-engine
Version: 1.0.0
Summary: Advanced stealth web scraping framework with browser fingerprinting and network obfuscation
Author-email: Chameleon Engine Contributors <maintainers@chameleon-engine.com>
Maintainer-email: Chameleon Engine Contributors <maintainers@chameleon-engine.com>
License: MIT License
Project-URL: Homepage, https://github.com/your-org/chameleon-engine
Project-URL: Documentation, https://chameleon-engine.readthedocs.io
Project-URL: Repository, https://github.com/your-org/chameleon-engine.git
Project-URL: Bug Tracker, https://github.com/your-org/chameleon-engine/issues
Project-URL: Changelog, https://github.com/your-org/chameleon-engine/blob/main/CHANGELOG.md
Project-URL: Discussions, https://github.com/your-org/chameleon-engine/discussions
Keywords: web-scraping,browser-fingerprinting,stealth-scraping,anti-bot,automation,data-collection,fingerprinting,proxy,microservices
Classifier: Development Status :: 5 - Production/Stable
Classifier: Intended Audience :: Developers
Classifier: License :: OSI Approved :: MIT License
Classifier: Operating System :: OS Independent
Classifier: Programming Language :: Python :: 3
Classifier: Programming Language :: Python :: 3.8
Classifier: Programming Language :: Python :: 3.9
Classifier: Programming Language :: Python :: 3.10
Classifier: Programming Language :: Python :: 3.11
Classifier: Programming Language :: Python :: 3.12
Classifier: Topic :: Internet :: WWW/HTTP :: Indexing/Search
Classifier: Topic :: Software Development :: Libraries :: Python Modules
Classifier: Topic :: Internet :: WWW/HTTP :: Browsers
Classifier: Topic :: System :: Networking
Classifier: Typing :: Typed
Requires-Python: >=3.8
License-File: LICENSE
Requires-Dist: playwright>=1.40.0
Requires-Dist: pydantic>=2.0.0
Requires-Dist: pydantic-settings>=2.0.0
Requires-Dist: numpy>=1.24.0
Requires-Dist: scipy>=1.10.0
Requires-Dist: requests>=2.25.0
Requires-Dist: httpx>=0.25.0
Requires-Dist: aiofiles>=23.0.0
Requires-Dist: tenacity>=8.2.0
Provides-Extra: core
Requires-Dist: playwright>=1.40.0; extra == "core"
Requires-Dist: pydantic>=2.0.0; extra == "core"
Requires-Dist: numpy>=1.24.0; extra == "core"
Requires-Dist: scipy>=1.10.0; extra == "core"
Requires-Dist: requests>=2.25.0; extra == "core"
Requires-Dist: httpx>=0.25.0; extra == "core"
Requires-Dist: aiofiles>=23.0.0; extra == "core"
Provides-Extra: dev
Requires-Dist: chameleon-engine[core]; extra == "dev"
Requires-Dist: pytest>=7.4.0; extra == "dev"
Requires-Dist: pytest-asyncio>=0.21.0; extra == "dev"
Requires-Dist: pytest-cov>=4.1.0; extra == "dev"
Requires-Dist: pytest-json-report>=1.5.0; extra == "dev"
Requires-Dist: pytest-mock>=3.11.0; extra == "dev"
Requires-Dist: pytest-xdist>=3.3.0; extra == "dev"
Requires-Dist: pytest-benchmark>=4.0.0; extra == "dev"
Requires-Dist: black>=23.7.0; extra == "dev"
Requires-Dist: ruff>=0.0.280; extra == "dev"
Requires-Dist: mypy>=1.5.0; extra == "dev"
Requires-Dist: pre-commit>=3.3.0; extra == "dev"
Requires-Dist: python-lsp-server>=1.7.0; extra == "dev"
Requires-Dist: tenacity>=8.2.0; extra == "dev"
Requires-Dist: psutil>=5.9.0; extra == "dev"
Requires-Dist: asyncio-throttle>=1.0.0; extra == "dev"
Requires-Dist: pillow>=10.0.0; extra == "dev"
Provides-Extra: stealth
Requires-Dist: chameleon-engine[core]; extra == "stealth"
Requires-Dist: patchright>=1.40.0; extra == "stealth"
Provides-Extra: fingerprint
Requires-Dist: chameleon-engine[core]; extra == "fingerprint"
Requires-Dist: fastapi>=0.104.0; extra == "fingerprint"
Requires-Dist: uvicorn>=0.24.0; extra == "fingerprint"
Requires-Dist: sqlalchemy>=2.0.0; extra == "fingerprint"
Requires-Dist: alembic>=1.12.0; extra == "fingerprint"
Provides-Extra: database
Requires-Dist: chameleon-engine[core]; extra == "database"
Requires-Dist: psycopg2-binary>=2.9.0; extra == "database"
Requires-Dist: sqlalchemy>=2.0.0; extra == "database"
Requires-Dist: alembic>=1.12.0; extra == "database"
Provides-Extra: scraping
Requires-Dist: chameleon-engine[core]; extra == "scraping"
Requires-Dist: beautifulsoup4>=4.12.0; extra == "scraping"
Requires-Dist: scrapy>=2.11.0; extra == "scraping"
Provides-Extra: services
Requires-Dist: chameleon-engine[core,database,fingerprint,scraping]; extra == "services"
Provides-Extra: full
Requires-Dist: chameleon-engine[core,database,fingerprint,scraping,services,stealth]; extra == "full"
Provides-Extra: all
Requires-Dist: chameleon-engine[full]; extra == "all"
Dynamic: license-file
